cifter/__init__.py
cifter/cifdocument.py
cifter/cifter.py
cifter/errors.py
cifter/parser.py
cifter/train_schedule.py
tests/__init__.py
tests/test_integration.py
tests/test_parser.py
cifter-0.0.1.dist-info/LICENSE
cifter-0.0.1.dist-info/METADATA
cifter-0.0.1.dist-info/WHEEL
cifter-0.0.1.dist-info/top_level.txt
cifter-0.0.1.dist-info/RECORD
