Metadata-Version: 2.1
Name: cifter
Version: 0.0.1
Summary: An Python3 ATOC file parser
Home-page: https://github.com/simonrankine/cifter
Author: Simon Rankine
Author-email: cifter@rankine.me
License: UNKNOWN
Platform: UNKNOWN
Classifier: Programming Language :: Python :: 3
Classifier: License :: OSI Approved :: Apache Software License
Classifier: Operating System :: OS Independent
Requires-Python: >=3.6
